example_package_anavarro/__init__.py
example_package_anavarro/example.py
example_package_anavarro-0.0.2.dist-info/METADATA
example_package_anavarro-0.0.2.dist-info/WHEEL
example_package_anavarro-0.0.2.dist-info/top_level.txt
example_package_anavarro-0.0.2.dist-info/RECORD
