Metadata-Version: 2.1
Name: example_package_anavarro
Version: 0.0.2
Summary: Suma de numero
Author-email: Alvaro <a.navarrogg@gmail.com>
License: MIT
Project-URL: Homepage, https://github.com/pypa/sampleproject
Project-URL: Issues, https://github.com/pypa/sampleproject/issues
Classifier: Programming Language :: Python :: 3
Classifier: Operating System :: OS Independent
Requires-Python: >=3.8
